LICENSE.txt
MANIFEST.in
README.md
setup.cfg
setup.py
django_cloudspotlicense/__init__.py
django_cloudspotlicense/admin.py
django_cloudspotlicense/apps.py
django_cloudspotlicense/config.py
django_cloudspotlicense/context_processors.py
django_cloudspotlicense/helpers.py
django_cloudspotlicense/mixins.py
django_cloudspotlicense/models.py
django_cloudspotlicense/tests.py
django_cloudspotlicense/urls.py
django_cloudspotlicense/utils.py
django_cloudspotlicense/views.py
django_cloudspotlicense.egg-info/PKG-INFO
django_cloudspotlicense.egg-info/SOURCES.txt
django_cloudspotlicense.egg-info/dependency_links.txt
django_cloudspotlicense.egg-info/requires.txt
django_cloudspotlicense.egg-info/top_level.txt
django_cloudspotlicense/migrations/0001_initial.py
django_cloudspotlicense/migrations/0002_cloudspotcompany_users.py
django_cloudspotlicense/migrations/0003_alter_cloudspotcompany_users.py
django_cloudspotlicense/migrations/__init__.py
django_cloudspotlicense/templates/auth/login.html
django_cloudspotlicense/templates/auth/select_company.html
django_cloudspotlicense/templatetags/__init__.py
django_cloudspotlicense/templatetags/license_tags.py