Metadata-Version: 2.1
Name: django-cloudspotlicense
Version: 6.2.0
Summary: Django package to integrate the authentication of the Cloudspot License Server in other django applications
Home-page: https://github.com/Ecosy-EU/django-cloudspotlicense
Author: Alexander Schillemans
Author-email: alexander.schillemans@lhs.global
License: GPL-3.0-or-later
Download-URL: https://github.com/Ecosy-EU/django-cloudspotlicense/archive/refs/tags/6.2.0.tar.gz
Keywords: cloudspot,django
Platform: UNKNOWN
Classifier: Development Status :: 3 - Alpha
Classifier: Intended Audience :: Developers
Classifier: Topic :: Software Development :: Build Tools
Classifier: License :: OSI Approved :: GNU General Public License v3 or later (GPLv3+)
Classifier: Programming Language :: Python :: 3.6
License-File: LICENSE.txt
